d8s_dates/__init__.py
d8s_dates/dates_and_times.py
tests/__init__.py
tests/test_dates_and_times.py
d8s_dates-0.7.0.dist-info/COPYING
d8s_dates-0.7.0.dist-info/COPYING.LESSER
d8s_dates-0.7.0.dist-info/METADATA
d8s_dates-0.7.0.dist-info/WHEEL
d8s_dates-0.7.0.dist-info/top_level.txt
d8s_dates-0.7.0.dist-info/zip-safe
d8s_dates-0.7.0.dist-info/RECORD
